automated_stock_rl/__init__.py
automated_stock_rl/package.py
automated_stock_rl/RL_algorithms/DQN.py
automated_stock_rl/RL_algorithms/__init__.py
automated_stock_rl/preprocessing/__init__.py
automated_stock_rl/preprocessing/data_scraping.py
automated_stock_rl-18.0.dist-info/METADATA
automated_stock_rl-18.0.dist-info/WHEEL
automated_stock_rl-18.0.dist-info/top_level.txt
automated_stock_rl-18.0.dist-info/RECORD
