Metadata-Version: 2.1
Name: automated-stock-rl
Version: 18.0
Summary: Automated Stock Reinforcement Learning
Home-page: https://github.com/noahweber1/automated_stock_rl
Author: Noah Weber
Author-email: noahweber53@ygmail.com
License: UNKNOWN
Download-URL: https://github.com/noahweber1/automated_stock_rl
Keywords: Auto_ML
Platform: UNKNOWN
Classifier: Development Status :: 4 - Beta
Classifier: Intended Audience :: Developers
Classifier: Programming Language :: Python :: 3
Classifier: Topic :: Scientific/Engineering
Classifier: Topic :: Scientific/Engineering :: Mathematics
Classifier: Topic :: Scientific/Engineering :: Artificial Intelligence
Requires-Dist: numpy (>=1.17)
Requires-Dist: pandas (>=0.24)
